prawvents/__init__.py
prawvents/main.py
prawvents-0.1.dist-info/LICENSE
prawvents-0.1.dist-info/METADATA
prawvents-0.1.dist-info/WHEEL
prawvents-0.1.dist-info/top_level.txt
prawvents-0.1.dist-info/RECORD
