Metadata-Version: 2.1
Name: prawvents
Version: 0.1
Summary: A Small wrapper for PRAW that allows for Event-based bots
Home-page: http://github.com/laundmo/prawvents
Author: Laurin Schmidt
Author-email: laurinschmidt2001@gmail.com
License: MIT
Keywords: prawvents praw reddit api wrapper
Platform: UNKNOWN
Classifier: Development Status :: 5 - Production/Stable
Classifier: Environment :: Console
Classifier: Intended Audience :: Developers
Classifier: License :: OSI Approved :: BSD License
Classifier: Natural Language :: English
Classifier: Operating System :: OS Independent
Classifier: Programming Language :: Python
Classifier: Programming Language :: Python :: 3
Classifier: Programming Language :: Python :: 3.6
Classifier: Programming Language :: Python :: 3.7
Classifier: Programming Language :: Python :: 3.8
Classifier: Programming Language :: Python :: 3.9
Classifier: Topic :: Utilities
Requires-Dist: praw
